rest_playbook_micro/__init__.py
rest_playbook_micro/_play.py
rest_playbook_micro/_playbook.py
rest_playbook_micro/_result.py
rest_playbook_micro/_scenario.py
rest_playbook_micro/_scenarios.py
rest_playbook_micro/_utils.py
rest_playbook_micro/_variable.py
rest_playbook_micro/_variables.py
rest_playbook_micro/assertion.py
rest_playbook_micro/rest_playbook.py
rest_playbook_micro-0.1.3.dist-info/METADATA
rest_playbook_micro-0.1.3.dist-info/WHEEL
rest_playbook_micro-0.1.3.dist-info/licenses/LICENSE
rest_playbook_micro-0.1.3.dist-info/RECORD
