Metadata-Version: 2.3
Name: rest_playbook_micro
Version: 0.1.3
Summary: A REST client playbook module, used to run rest scenarios with substitution and other features
Author: Samuel Shiels
License-File: LICENSE
Classifier: License :: OSI Approved :: MIT License
Classifier: Operating System :: POSIX :: Linux
Classifier: Programming Language :: Python :: 3
Requires-Python: >=3.11.5
Requires-Dist: rest-client-micro>=0.3.1
Requires-Dist: uuid
